graphcast/README.md
graphcast/__init__.py
graphcast/caster.py
graphcast/logging.conf
graphcast/onto.py
graphcast/architecture/__init__.py
graphcast/architecture/actor.py
graphcast/architecture/actor_util.py
graphcast/architecture/edge.py
graphcast/architecture/onto.py
graphcast/architecture/resource.py
graphcast/architecture/schema.py
graphcast/architecture/transform.py
graphcast/architecture/util.py
graphcast/architecture/vertex.py
graphcast/cli/__init__.py
graphcast/cli/ingest.py
graphcast/cli/manage_dbs.py
graphcast/cli/plot_schema.py
graphcast/cli/xml2json.py
graphcast/db/__init__.py
graphcast/db/connection.py
graphcast/db/manager.py
graphcast/db/util.py
graphcast/db/arango/__init__.py
graphcast/db/arango/conn.py
graphcast/db/arango/query.py
graphcast/db/arango/util.py
graphcast/db/neo4j/__init__.py
graphcast/db/neo4j/conn.py
graphcast/filter/__init__.py
graphcast/filter/onto.py
graphcast/plot/__init__.py
graphcast/plot/plotter.py
graphcast/util/__init__.py
graphcast/util/chunker.py
graphcast/util/merge.py
graphcast/util/misc.py
graphcast/util/onto.py
graphcast/util/transform.py
graphcast-0.14.2.dist-info/METADATA
graphcast-0.14.2.dist-info/WHEEL
graphcast-0.14.2.dist-info/entry_points.txt
graphcast-0.14.2.dist-info/licenses/LICENSE
graphcast-0.14.2.dist-info/RECORD
